pyside_material/__init__.py
pyside_material/material.css.template
pyside_material/fonts/DejaVuMathTeXGyre.ttf
pyside_material/fonts/DejaVuSans-Bold.ttf
pyside_material/fonts/DejaVuSans-BoldOblique.ttf
pyside_material/fonts/DejaVuSans-ExtraLight.ttf
pyside_material/fonts/DejaVuSans-Oblique.ttf
pyside_material/fonts/DejaVuSans.ttf
pyside_material/fonts/DejaVuSansCondensed-Bold.ttf
pyside_material/fonts/DejaVuSansCondensed-BoldOblique.ttf
pyside_material/fonts/DejaVuSansCondensed-Oblique.ttf
pyside_material/fonts/DejaVuSansCondensed.ttf
pyside_material/fonts/DejaVuSansMono-Bold.ttf
pyside_material/fonts/DejaVuSansMono-BoldOblique.ttf
pyside_material/fonts/DejaVuSansMono-Oblique.ttf
pyside_material/fonts/DejaVuSansMono.ttf
pyside_material/fonts/DejaVuSerif-Bold.ttf
pyside_material/fonts/DejaVuSerif-BoldItalic.ttf
pyside_material/fonts/DejaVuSerif-Italic.ttf
pyside_material/fonts/DejaVuSerif.ttf
pyside_material/fonts/DejaVuSerifCondensed-Bold.ttf
pyside_material/fonts/DejaVuSerifCondensed-BoldItalic.ttf
pyside_material/fonts/DejaVuSerifCondensed-Italic.ttf
pyside_material/fonts/DejaVuSerifCondensed.ttf
pyside_material/fonts/Roboto-Black.ttf
pyside_material/fonts/Roboto-BlackItalic.ttf
pyside_material/fonts/Roboto-Bold.ttf
pyside_material/fonts/Roboto-BoldItalic.ttf
pyside_material/fonts/Roboto-Italic.ttf
pyside_material/fonts/Roboto-Light.ttf
pyside_material/fonts/Roboto-LightItalic.ttf
pyside_material/fonts/Roboto-Medium.ttf
pyside_material/fonts/Roboto-MediumItalic.ttf
pyside_material/fonts/Roboto-Regular.ttf
pyside_material/fonts/Roboto-Thin.ttf
pyside_material/fonts/Roboto-ThinItalic.ttf
pyside_material/fonts/RobotoCondensed-Bold.ttf
pyside_material/fonts/RobotoCondensed-BoldItalic.ttf
pyside_material/fonts/RobotoCondensed-Italic.ttf
pyside_material/fonts/RobotoCondensed-Light.ttf
pyside_material/fonts/RobotoCondensed-LightItalic.ttf
pyside_material/fonts/RobotoCondensed-Regular.ttf
pyside_material/resources/__init__.py
pyside_material/resources/generate.py
pyside_material-1.17.dist-info/LICENSE
pyside_material-1.17.dist-info/METADATA
pyside_material-1.17.dist-info/WHEEL
pyside_material-1.17.dist-info/top_level.txt
pyside_material-1.17.dist-info/RECORD
