Metadata-Version: 2.1
Name: pyside-material
Version: 1.17
Summary: PySide2 stylesheet.
Home-page: UNKNOWN
Author: Yeison Cardona
Author-email: yencardonaal@unal.edu.co
Maintainer: Yeison Cardona
Maintainer-email: yencardonaal@unal.edu.co
License: BSD-2-Clause
Download-URL: https://github.com/UN-GCPDS/pyside-material
Platform: UNKNOWN
Requires-Python: >=3.6
Requires-Dist: pyside2
